{
  "resourceType" : "CodeSystem",
  "id" : "fr-core-cs-discipline-equipement",
  "meta" : {
    "profile" : ["http://hl7.org/fhir/StructureDefinition/shareablecodesystem|4.0.1"]
  },
  "text" : {
    "status" : "generated",
    "div" : "<div xmlns=\"http://www.w3.org/1999/xhtml\"><p class=\"res-header-id\"><b>Narratif généré : CodeSystem fr-core-cs-discipline-equipement</b></p><a name=\"fr-core-cs-discipline-equipement\"> </a><a name=\"hcfr-core-cs-discipline-equipement\"> </a><div style=\"display: inline-block; background-color: #d9e0e7; padding: 6px; margin: 4px; border: 1px solid #8da1b4; border-radius: 5px; line-height: 60%\"><p style=\"margin-bottom: 0px\"/><p style=\"margin-bottom: 0px\">Profil: <a href=\"http://hl7.org/fhir/R4/shareablecodesystem.html\">Shareable CodeSystemversion : null4.0.1)</a></p></div><p>This case-sensitive code system <code>https://hl7.fr/ig/fhir/core/CodeSystem/fr-core-cs-discipline-equipement</code> defines the following codes:</p><table class=\"codes\"><tr><td style=\"white-space:nowrap\"><b>Code</b></td><td><b>Affichage</b></td></tr><tr><td style=\"white-space:nowrap\">23<a name=\"fr-core-cs-discipline-equipement-23\"> </a></td><td>Stérilisation</td></tr><tr><td style=\"white-space:nowrap\">34<a name=\"fr-core-cs-discipline-equipement-34\"> </a></td><td>Radiostandard</td></tr><tr><td style=\"white-space:nowrap\">35<a name=\"fr-core-cs-discipline-equipement-35\"> </a></td><td>Scanographie X</td></tr><tr><td style=\"white-space:nowrap\">36<a name=\"fr-core-cs-discipline-equipement-36\"> </a></td><td>Neuroradiologie</td></tr><tr><td style=\"white-space:nowrap\">37<a name=\"fr-core-cs-discipline-equipement-37\"> </a></td><td>Hémodynamique</td></tr><tr><td style=\"white-space:nowrap\">45<a name=\"fr-core-cs-discipline-equipement-45\"> </a></td><td>Explorations fonctionnelles cardiovasculaires</td></tr><tr><td style=\"white-space:nowrap\">46<a name=\"fr-core-cs-discipline-equipement-46\"> </a></td><td>Explorations fonctionnelles néphrologiques</td></tr><tr><td style=\"white-space:nowrap\">47<a name=\"fr-core-cs-discipline-equipement-47\"> </a></td><td>Explorations fonctionnelles pneumologiques</td></tr><tr><td style=\"white-space:nowrap\">48<a name=\"fr-core-cs-discipline-equipement-48\"> </a></td><td>Explorations fonctionnelles neurologiques</td></tr><tr><td style=\"white-space:nowrap\">49<a name=\"fr-core-cs-discipline-equipement-49\"> </a></td><td>Explorations fonctionnelles du tube digestif</td></tr><tr><td style=\"white-space:nowrap\">50<a name=\"fr-core-cs-discipline-equipement-50\"> </a></td><td>Autres explorations fonctionnelles spécialisées</td></tr><tr><td style=\"white-space:nowrap\">51<a name=\"fr-core-cs-discipline-equipement-51\"> </a></td><td>Explorations fonctionnelles cardiovasculaires et néphrologiques</td></tr><tr><td style=\"white-space:nowrap\">52<a name=\"fr-core-cs-discipline-equipement-52\"> </a></td><td>Explorations fonctionnelles cardiovasculaires et pneumologiques</td></tr><tr><td style=\"white-space:nowrap\">53<a name=\"fr-core-cs-discipline-equipement-53\"> </a></td><td>Autres explorations fonctionnelles polyvalentes</td></tr><tr><td style=\"white-space:nowrap\">55<a name=\"fr-core-cs-discipline-equipement-55\"> </a></td><td>Réeducation fonctionnelle</td></tr><tr><td style=\"white-space:nowrap\">56<a name=\"fr-core-cs-discipline-equipement-56\"> </a></td><td>Ergothérapie</td></tr><tr><td style=\"white-space:nowrap\">57<a name=\"fr-core-cs-discipline-equipement-57\"> </a></td><td>Hydrothérapie</td></tr><tr><td style=\"white-space:nowrap\">58<a name=\"fr-core-cs-discipline-equipement-58\"> </a></td><td>Kinésithérapie</td></tr><tr><td style=\"white-space:nowrap\">59<a name=\"fr-core-cs-discipline-equipement-59\"> </a></td><td>Orthophonie</td></tr><tr><td style=\"white-space:nowrap\">60<a name=\"fr-core-cs-discipline-equipement-60\"> </a></td><td>Orthoptie</td></tr><tr><td style=\"white-space:nowrap\">61<a name=\"fr-core-cs-discipline-equipement-61\"> </a></td><td>Autres rééducations spécialisées</td></tr><tr><td style=\"white-space:nowrap\">62<a name=\"fr-core-cs-discipline-equipement-62\"> </a></td><td>Anatomie pathologique (anatomie et cytologie pathologique)</td></tr><tr><td style=\"white-space:nowrap\">63<a name=\"fr-core-cs-discipline-equipement-63\"> </a></td><td>Bactériologie</td></tr><tr><td style=\"white-space:nowrap\">64<a name=\"fr-core-cs-discipline-equipement-64\"> </a></td><td>Biochimie générale et spécialisée</td></tr><tr><td style=\"white-space:nowrap\">70<a name=\"fr-core-cs-discipline-equipement-70\"> </a></td><td>Embryologie clinique</td></tr><tr><td style=\"white-space:nowrap\">79<a name=\"fr-core-cs-discipline-equipement-79\"> </a></td><td>Parasitologie-mycologie</td></tr><tr><td style=\"white-space:nowrap\">80<a name=\"fr-core-cs-discipline-equipement-80\"> </a></td><td>Pharmacologie-toxicologie</td></tr><tr><td style=\"white-space:nowrap\">83<a name=\"fr-core-cs-discipline-equipement-83\"> </a></td><td>Virologie</td></tr><tr><td style=\"white-space:nowrap\">86<a name=\"fr-core-cs-discipline-equipement-86\"> </a></td><td>Vaccination </td></tr><tr><td style=\"white-space:nowrap\">87<a name=\"fr-core-cs-discipline-equipement-87\"> </a></td><td>Consultation antitabac</td></tr><tr><td style=\"white-space:nowrap\">88<a name=\"fr-core-cs-discipline-equipement-88\"> </a></td><td>Médecine légale</td></tr><tr><td style=\"white-space:nowrap\">89<a name=\"fr-core-cs-discipline-equipement-89\"> </a></td><td>Médecine préventive et de santé publique</td></tr><tr><td style=\"white-space:nowrap\">90<a name=\"fr-core-cs-discipline-equipement-90\"> </a></td><td>Autres consultations et soins externes</td></tr><tr><td style=\"white-space:nowrap\">91<a name=\"fr-core-cs-discipline-equipement-91\"> </a></td><td>Fabrication-préparation de produits pharmaceutiques</td></tr><tr><td style=\"white-space:nowrap\">92<a name=\"fr-core-cs-discipline-equipement-92\"> </a></td><td>Distribution de produits pharmaceutiques</td></tr><tr><td style=\"white-space:nowrap\">93<a name=\"fr-core-cs-discipline-equipement-93\"> </a></td><td>Distribution d'autres biens médicaux</td></tr><tr><td style=\"white-space:nowrap\">94<a name=\"fr-core-cs-discipline-equipement-94\"> </a></td><td>Activité de pharmacocinétique (Autre activité d'analyse et de recherche sur les médicaments)</td></tr><tr><td style=\"white-space:nowrap\">95<a name=\"fr-core-cs-discipline-equipement-95\"> </a></td><td>Autres activités (fabrication autres biens médicaux, prothèses, etc)</td></tr><tr><td style=\"white-space:nowrap\">96<a name=\"fr-core-cs-discipline-equipement-96\"> </a></td><td>Prélèvement à but scientifique (autopsie) et vérification de diagnostics</td></tr><tr><td style=\"white-space:nowrap\">97<a name=\"fr-core-cs-discipline-equipement-97\"> </a></td><td>Anesthésiologie (consultation)</td></tr><tr><td style=\"white-space:nowrap\">99<a name=\"fr-core-cs-discipline-equipement-99\"> </a></td><td>Activité de pharmacotoxico-vigilance</td></tr><tr><td style=\"white-space:nowrap\">108<a name=\"fr-core-cs-discipline-equipement-108\"> </a></td><td>Médecine pédiatrique (hors unité d'oncologie médicale, spécialisée ou non)</td></tr><tr><td style=\"white-space:nowrap\">112<a name=\"fr-core-cs-discipline-equipement-112\"> </a></td><td>Néonatologie sans SI</td></tr><tr><td style=\"white-space:nowrap\">145<a name=\"fr-core-cs-discipline-equipement-145\"> </a></td><td>Traitement des grands brûlés (hors réanimation et surveillance continue grands brûlés)</td></tr><tr><td style=\"white-space:nowrap\">151<a name=\"fr-core-cs-discipline-equipement-151\"> </a></td><td>Neurochirurgie</td></tr><tr><td style=\"white-space:nowrap\">164<a name=\"fr-core-cs-discipline-equipement-164\"> </a></td><td>Gynécologie seule</td></tr><tr><td style=\"white-space:nowrap\">165<a name=\"fr-core-cs-discipline-equipement-165\"> </a></td><td>Obstétrique seule</td></tr><tr><td style=\"white-space:nowrap\">176<a name=\"fr-core-cs-discipline-equipement-176\"> </a></td><td>Soins de longue durée pour personnes ayant perdu leur autonomie de vie</td></tr><tr><td style=\"white-space:nowrap\">197<a name=\"fr-core-cs-discipline-equipement-197\"> </a></td><td>Consultations et soins dentaires</td></tr><tr><td style=\"white-space:nowrap\">200<a name=\"fr-core-cs-discipline-equipement-200\"> </a></td><td>Transfusion sanguine (laboratoire)</td></tr><tr><td style=\"white-space:nowrap\">201<a name=\"fr-core-cs-discipline-equipement-201\"> </a></td><td>Banque de sperme</td></tr><tr><td style=\"white-space:nowrap\">202<a name=\"fr-core-cs-discipline-equipement-202\"> </a></td><td>Banques d'organes</td></tr><tr><td style=\"white-space:nowrap\">203<a name=\"fr-core-cs-discipline-equipement-203\"> </a></td><td>Dispensaire de soins</td></tr><tr><td style=\"white-space:nowrap\">204<a name=\"fr-core-cs-discipline-equipement-204\"> </a></td><td>Soins infirmiers</td></tr><tr><td style=\"white-space:nowrap\">205<a name=\"fr-core-cs-discipline-equipement-205\"> </a></td><td>Lutte contre les maladies sexuellement transmissibles</td></tr><tr><td style=\"white-space:nowrap\">218<a name=\"fr-core-cs-discipline-equipement-218\"> </a></td><td>Vaccination BCG</td></tr><tr><td style=\"white-space:nowrap\">235<a name=\"fr-core-cs-discipline-equipement-235\"> </a></td><td>Soins intensifs en néonatologie</td></tr><tr><td style=\"white-space:nowrap\">241<a name=\"fr-core-cs-discipline-equipement-241\"> </a></td><td>Hygiène alimentaire (activité des centres d'hygiène alimentaire notamment)</td></tr><tr><td style=\"white-space:nowrap\">309<a name=\"fr-core-cs-discipline-equipement-309\"> </a></td><td>Interruption volontaire de grossesse</td></tr><tr><td style=\"white-space:nowrap\">384<a name=\"fr-core-cs-discipline-equipement-384\"> </a></td><td>Protection maternelle et infantile (centre de PMI ou dispensaire de PMI)</td></tr><tr><td style=\"white-space:nowrap\">385<a name=\"fr-core-cs-discipline-equipement-385\"> </a></td><td>Consultations prénuptiales, prénatales ou postnatales</td></tr><tr><td style=\"white-space:nowrap\">386<a name=\"fr-core-cs-discipline-equipement-386\"> </a></td><td>Consultations de protection infantile</td></tr><tr><td style=\"white-space:nowrap\">389<a name=\"fr-core-cs-discipline-equipement-389\"> </a></td><td>Lutte contre la stérilité</td></tr><tr><td style=\"white-space:nowrap\">390<a name=\"fr-core-cs-discipline-equipement-390\"> </a></td><td>Consultations de conseil génétique</td></tr><tr><td style=\"white-space:nowrap\">391<a name=\"fr-core-cs-discipline-equipement-391\"> </a></td><td>Consultations de planification ou d'éducation familiale</td></tr><tr><td style=\"white-space:nowrap\">392<a name=\"fr-core-cs-discipline-equipement-392\"> </a></td><td>Information, consultation ou conseil familial</td></tr><tr><td style=\"white-space:nowrap\">394<a name=\"fr-core-cs-discipline-equipement-394\"> </a></td><td>Lactarium</td></tr><tr><td style=\"white-space:nowrap\">395<a name=\"fr-core-cs-discipline-equipement-395\"> </a></td><td>Guidance parentale</td></tr><tr><td style=\"white-space:nowrap\">396<a name=\"fr-core-cs-discipline-equipement-396\"> </a></td><td>Guidance infantile</td></tr><tr><td style=\"white-space:nowrap\">446<a name=\"fr-core-cs-discipline-equipement-446\"> </a></td><td>Médecine scolaire</td></tr><tr><td style=\"white-space:nowrap\">447<a name=\"fr-core-cs-discipline-equipement-447\"> </a></td><td>Médecine universitaire</td></tr><tr><td style=\"white-space:nowrap\">448<a name=\"fr-core-cs-discipline-equipement-448\"> </a></td><td>Médecine sportive</td></tr><tr><td style=\"white-space:nowrap\">452<a name=\"fr-core-cs-discipline-equipement-452\"> </a></td><td>Aide aux insuffisants respiratoires</td></tr><tr><td style=\"white-space:nowrap\">552<a name=\"fr-core-cs-discipline-equipement-552\"> </a></td><td>Entraînement à l'hémodialyse </td></tr><tr><td style=\"white-space:nowrap\">553<a name=\"fr-core-cs-discipline-equipement-553\"> </a></td><td>Entraînement à la dialyse péritonéale</td></tr><tr><td style=\"white-space:nowrap\">555<a name=\"fr-core-cs-discipline-equipement-555\"> </a></td><td>Dialyse péritonéale automatisée à domicile</td></tr><tr><td style=\"white-space:nowrap\">556<a name=\"fr-core-cs-discipline-equipement-556\"> </a></td><td>Dialyse péritonéale continue ambulatoire à domicile</td></tr><tr><td style=\"white-space:nowrap\">596<a name=\"fr-core-cs-discipline-equipement-596\"> </a></td><td>Médecine du travail</td></tr><tr><td style=\"white-space:nowrap\">631<a name=\"fr-core-cs-discipline-equipement-631\"> </a></td><td>Gynécologie seule</td></tr><tr><td style=\"white-space:nowrap\">634<a name=\"fr-core-cs-discipline-equipement-634\"> </a></td><td>Laboratoire de  radio-isotopes (Médecine nucléaire in vivo)</td></tr><tr><td style=\"white-space:nowrap\">635<a name=\"fr-core-cs-discipline-equipement-635\"> </a></td><td>Réanimation néonatale</td></tr><tr><td style=\"white-space:nowrap\">645<a name=\"fr-core-cs-discipline-equipement-645\"> </a></td><td>Oxygénothérapie isolée (insuffisants respiratoires)</td></tr><tr><td style=\"white-space:nowrap\">646<a name=\"fr-core-cs-discipline-equipement-646\"> </a></td><td>Assistance ventilatoire sans trachéotomie (insuffisants respiratoires)</td></tr><tr><td style=\"white-space:nowrap\">647<a name=\"fr-core-cs-discipline-equipement-647\"> </a></td><td>Assistance ventilatoire endotrachéale (insuffisants respiratoires)</td></tr><tr><td style=\"white-space:nowrap\">648<a name=\"fr-core-cs-discipline-equipement-648\"> </a></td><td>Trachéotomie isolée (insuffisants respiratoires)</td></tr><tr><td style=\"white-space:nowrap\">665<a name=\"fr-core-cs-discipline-equipement-665\"> </a></td><td>Fabrication et distribution indifférenciées de produits pharmaceutiques</td></tr><tr><td style=\"white-space:nowrap\">700<a name=\"fr-core-cs-discipline-equipement-700\"> </a></td><td>Fabrication, conditionnement et importation de produits cosmétiques et de produits d'hygiène corp.</td></tr><tr><td style=\"white-space:nowrap\">701<a name=\"fr-core-cs-discipline-equipement-701\"> </a></td><td>Fabrication de produits diététiques</td></tr><tr><td style=\"white-space:nowrap\">702<a name=\"fr-core-cs-discipline-equipement-702\"> </a></td><td>Préparation et vente en gros de produits vétérinaires</td></tr><tr><td style=\"white-space:nowrap\">703<a name=\"fr-core-cs-discipline-equipement-703\"> </a></td><td>Fabrication (ou importation) de radio-éléments artificiels</td></tr><tr><td style=\"white-space:nowrap\">704<a name=\"fr-core-cs-discipline-equipement-704\"> </a></td><td>Détention d'animaux en vue de l'expérimentation des médicaments</td></tr><tr><td style=\"white-space:nowrap\">705<a name=\"fr-core-cs-discipline-equipement-705\"> </a></td><td>Fabrication d'objets contraceptifs</td></tr><tr><td style=\"white-space:nowrap\">723<a name=\"fr-core-cs-discipline-equipement-723\"> </a></td><td>Hémodialyse à domicile</td></tr><tr><td style=\"white-space:nowrap\">726<a name=\"fr-core-cs-discipline-equipement-726\"> </a></td><td>Consultations multidisciplines regroupées (médecine, chirurgie et autres spécialités)</td></tr><tr><td style=\"white-space:nowrap\">727<a name=\"fr-core-cs-discipline-equipement-727\"> </a></td><td>Consultations externes indifférenciées</td></tr><tr><td style=\"white-space:nowrap\">743<a name=\"fr-core-cs-discipline-equipement-743\"> </a></td><td>Immunohématologie</td></tr><tr><td style=\"white-space:nowrap\">745<a name=\"fr-core-cs-discipline-equipement-745\"> </a></td><td>Hémostase</td></tr><tr><td style=\"white-space:nowrap\">750<a name=\"fr-core-cs-discipline-equipement-750\"> </a></td><td>Tomographie</td></tr><tr><td style=\"white-space:nowrap\">751<a name=\"fr-core-cs-discipline-equipement-751\"> </a></td><td>Radiologie vasculaire</td></tr><tr><td style=\"white-space:nowrap\">752<a name=\"fr-core-cs-discipline-equipement-752\"> </a></td><td>Echographie sans autre indication (sai)</td></tr><tr><td style=\"white-space:nowrap\">753<a name=\"fr-core-cs-discipline-equipement-753\"> </a></td><td>Imagerie par résonance magnétique (IRM)</td></tr><tr><td style=\"white-space:nowrap\">754<a name=\"fr-core-cs-discipline-equipement-754\"> </a></td><td>Autres activités spécialisées d'imagerie médicale</td></tr><tr><td style=\"white-space:nowrap\">755<a name=\"fr-core-cs-discipline-equipement-755\"> </a></td><td>Explorations fonctionnelles en ORL</td></tr><tr><td style=\"white-space:nowrap\">756<a name=\"fr-core-cs-discipline-equipement-756\"> </a></td><td>Explorations fonctionnelles en ophtalmologie</td></tr><tr><td style=\"white-space:nowrap\">757<a name=\"fr-core-cs-discipline-equipement-757\"> </a></td><td>Recherche et expérimentation dans les services médico-techniques</td></tr><tr><td style=\"white-space:nowrap\">760<a name=\"fr-core-cs-discipline-equipement-760\"> </a></td><td>Salle de réveil</td></tr><tr><td style=\"white-space:nowrap\">761<a name=\"fr-core-cs-discipline-equipement-761\"> </a></td><td>Anesthésiologie et salle de réveil</td></tr><tr><td style=\"white-space:nowrap\">762<a name=\"fr-core-cs-discipline-equipement-762\"> </a></td><td>Bloc opératoire et stérilisation indifférenciés</td></tr><tr><td style=\"white-space:nowrap\">763<a name=\"fr-core-cs-discipline-equipement-763\"> </a></td><td>Pharmacie et stérilisation indifférenciées</td></tr><tr><td style=\"white-space:nowrap\">797<a name=\"fr-core-cs-discipline-equipement-797\"> </a></td><td>Hémodialyse en centre pour adulte</td></tr><tr><td style=\"white-space:nowrap\">798<a name=\"fr-core-cs-discipline-equipement-798\"> </a></td><td>Hémodialyse en centre pour enfant</td></tr><tr><td style=\"white-space:nowrap\">799<a name=\"fr-core-cs-discipline-equipement-799\"> </a></td><td>Assistance ventilatoire avec prothèse extrathoracique(insuffisants respiratoires)</td></tr><tr><td style=\"white-space:nowrap\">800<a name=\"fr-core-cs-discipline-equipement-800\"> </a></td><td>Assistance ventilatoire par pression positive continue ou autres techniques particulières agréées (insuffisants respiratoires)</td></tr><tr><td style=\"white-space:nowrap\">815<a name=\"fr-core-cs-discipline-equipement-815\"> </a></td><td>Echocardiologie</td></tr><tr><td style=\"white-space:nowrap\">816<a name=\"fr-core-cs-discipline-equipement-816\"> </a></td><td>Echographie abdominale</td></tr><tr><td style=\"white-space:nowrap\">817<a name=\"fr-core-cs-discipline-equipement-817\"> </a></td><td>Echographie en obstétrique</td></tr><tr><td style=\"white-space:nowrap\">818<a name=\"fr-core-cs-discipline-equipement-818\"> </a></td><td>Echographie vasculaire</td></tr><tr><td style=\"white-space:nowrap\">819<a name=\"fr-core-cs-discipline-equipement-819\"> </a></td><td>Autres échographies</td></tr><tr><td style=\"white-space:nowrap\">820<a name=\"fr-core-cs-discipline-equipement-820\"> </a></td><td>Collecte de sang</td></tr><tr><td style=\"white-space:nowrap\">821<a name=\"fr-core-cs-discipline-equipement-821\"> </a></td><td>Stockage-distribution de sang</td></tr><tr><td style=\"white-space:nowrap\">822<a name=\"fr-core-cs-discipline-equipement-822\"> </a></td><td>Production de produits sanguins</td></tr><tr><td style=\"white-space:nowrap\">823<a name=\"fr-core-cs-discipline-equipement-823\"> </a></td><td>Autres activités de transfusion sanguine</td></tr><tr><td style=\"white-space:nowrap\">824<a name=\"fr-core-cs-discipline-equipement-824\"> </a></td><td>Pharmacie d'établissement</td></tr><tr><td style=\"white-space:nowrap\">949<a name=\"fr-core-cs-discipline-equipement-949\"> </a></td><td>Recherche chirurgicale ou chirurgie expérimentale</td></tr><tr><td style=\"white-space:nowrap\">952<a name=\"fr-core-cs-discipline-equipement-952\"> </a></td><td>Recherche médicale</td></tr><tr><td style=\"white-space:nowrap\">953<a name=\"fr-core-cs-discipline-equipement-953\"> </a></td><td>Recherche pharmacologique</td></tr><tr><td style=\"white-space:nowrap\">954<a name=\"fr-core-cs-discipline-equipement-954\"> </a></td><td>Recherche pharmaceutique</td></tr><tr><td style=\"white-space:nowrap\">955<a name=\"fr-core-cs-discipline-equipement-955\"> </a></td><td>Recherche odontologique</td></tr><tr><td style=\"white-space:nowrap\">956<a name=\"fr-core-cs-discipline-equipement-956\"> </a></td><td>Recherche toxicologique</td></tr><tr><td style=\"white-space:nowrap\">996<a name=\"fr-core-cs-discipline-equipement-996\"> </a></td><td>Services extérieurs</td></tr><tr><td style=\"white-space:nowrap\">997<a name=\"fr-core-cs-discipline-equipement-997\"> </a></td><td>Discipline non dénommée ailleurs</td></tr></table></div>"
  },
  "url" : "https://hl7.fr/ig/fhir/core/CodeSystem/fr-core-cs-discipline-equipement",
  "version" : "2.2.0-ballot-2",
  "name" : "FRCoreCodeSystemDisciplineEquipement",
  "title" : "FR Core CodeSystem Discipline d'Equipement - nomenclature SAE",
  "status" : "draft",
  "experimental" : false,
  "date" : "2026-01-29T08:41:18+00:00",
  "publisher" : "Interop'Santé",
  "contact" : [{
    "name" : "Interop'Santé",
    "telecom" : [{
      "system" : "url",
      "value" : "http://interopsante.org"
    }]
  },
  {
    "name" : "InteropSanté",
    "telecom" : [{
      "system" : "email",
      "value" : "fhir@interopsante.org",
      "use" : "work"
    }]
  }],
  "description" : "La nomenclature de disciplines d'équipement est utilisée pour ventiler l'activité et le personnel entre les différentes disciplines de la section hôpital (MCO, PSY, HAD, SMR et SLD) et la discipline 'administration, services hôteliers et techniques'. La nomenclature des disciplines d’équipement s’applique aux unités fonctionnelles et aux sections issues du fichier de structure des établissements. Les disciplines sociales, médico-sociales et de formation n'apparaissent pas, car elles ne font pas partie du champ de la SAE.",
  "jurisdiction" : [{
    "coding" : [{
      "system" : "urn:iso:std:iso:3166",
      "code" : "FRA",
      "display" : "France"
    }]
  }],
  "caseSensitive" : true,
  "content" : "complete",
  "count" : 131,
  "concept" : [{
    "code" : "23",
    "display" : "Stérilisation"
  },
  {
    "code" : "34",
    "display" : "Radiostandard"
  },
  {
    "code" : "35",
    "display" : "Scanographie X"
  },
  {
    "code" : "36",
    "display" : "Neuroradiologie"
  },
  {
    "code" : "37",
    "display" : "Hémodynamique"
  },
  {
    "code" : "45",
    "display" : "Explorations fonctionnelles cardiovasculaires"
  },
  {
    "code" : "46",
    "display" : "Explorations fonctionnelles néphrologiques"
  },
  {
    "code" : "47",
    "display" : "Explorations fonctionnelles pneumologiques"
  },
  {
    "code" : "48",
    "display" : "Explorations fonctionnelles neurologiques"
  },
  {
    "code" : "49",
    "display" : "Explorations fonctionnelles du tube digestif"
  },
  {
    "code" : "50",
    "display" : "Autres explorations fonctionnelles spécialisées"
  },
  {
    "code" : "51",
    "display" : "Explorations fonctionnelles cardiovasculaires et néphrologiques"
  },
  {
    "code" : "52",
    "display" : "Explorations fonctionnelles cardiovasculaires et pneumologiques"
  },
  {
    "code" : "53",
    "display" : "Autres explorations fonctionnelles polyvalentes"
  },
  {
    "code" : "55",
    "display" : "Réeducation fonctionnelle"
  },
  {
    "code" : "56",
    "display" : "Ergothérapie"
  },
  {
    "code" : "57",
    "display" : "Hydrothérapie"
  },
  {
    "code" : "58",
    "display" : "Kinésithérapie"
  },
  {
    "code" : "59",
    "display" : "Orthophonie"
  },
  {
    "code" : "60",
    "display" : "Orthoptie"
  },
  {
    "code" : "61",
    "display" : "Autres rééducations spécialisées"
  },
  {
    "code" : "62",
    "display" : "Anatomie pathologique (anatomie et cytologie pathologique)"
  },
  {
    "code" : "63",
    "display" : "Bactériologie"
  },
  {
    "code" : "64",
    "display" : "Biochimie générale et spécialisée"
  },
  {
    "code" : "70",
    "display" : "Embryologie clinique"
  },
  {
    "code" : "79",
    "display" : "Parasitologie-mycologie"
  },
  {
    "code" : "80",
    "display" : "Pharmacologie-toxicologie"
  },
  {
    "code" : "83",
    "display" : "Virologie"
  },
  {
    "code" : "86",
    "display" : "Vaccination "
  },
  {
    "code" : "87",
    "display" : "Consultation antitabac"
  },
  {
    "code" : "88",
    "display" : "Médecine légale"
  },
  {
    "code" : "89",
    "display" : "Médecine préventive et de santé publique"
  },
  {
    "code" : "90",
    "display" : "Autres consultations et soins externes"
  },
  {
    "code" : "91",
    "display" : "Fabrication-préparation de produits pharmaceutiques"
  },
  {
    "code" : "92",
    "display" : "Distribution de produits pharmaceutiques"
  },
  {
    "code" : "93",
    "display" : "Distribution d'autres biens médicaux"
  },
  {
    "code" : "94",
    "display" : "Activité de pharmacocinétique (Autre activité d'analyse et de recherche sur les médicaments)"
  },
  {
    "code" : "95",
    "display" : "Autres activités (fabrication autres biens médicaux, prothèses, etc)"
  },
  {
    "code" : "96",
    "display" : "Prélèvement à but scientifique (autopsie) et vérification de diagnostics"
  },
  {
    "code" : "97",
    "display" : "Anesthésiologie (consultation)"
  },
  {
    "code" : "99",
    "display" : "Activité de pharmacotoxico-vigilance"
  },
  {
    "code" : "108",
    "display" : "Médecine pédiatrique (hors unité d'oncologie médicale, spécialisée ou non)"
  },
  {
    "code" : "112",
    "display" : "Néonatologie sans SI"
  },
  {
    "code" : "145",
    "display" : "Traitement des grands brûlés (hors réanimation et surveillance continue grands brûlés)"
  },
  {
    "code" : "151",
    "display" : "Neurochirurgie"
  },
  {
    "code" : "164",
    "display" : "Gynécologie seule"
  },
  {
    "code" : "165",
    "display" : "Obstétrique seule"
  },
  {
    "code" : "176",
    "display" : "Soins de longue durée pour personnes ayant perdu leur autonomie de vie"
  },
  {
    "code" : "197",
    "display" : "Consultations et soins dentaires"
  },
  {
    "code" : "200",
    "display" : "Transfusion sanguine (laboratoire)"
  },
  {
    "code" : "201",
    "display" : "Banque de sperme"
  },
  {
    "code" : "202",
    "display" : "Banques d'organes"
  },
  {
    "code" : "203",
    "display" : "Dispensaire de soins"
  },
  {
    "code" : "204",
    "display" : "Soins infirmiers"
  },
  {
    "code" : "205",
    "display" : "Lutte contre les maladies sexuellement transmissibles"
  },
  {
    "code" : "218",
    "display" : "Vaccination BCG"
  },
  {
    "code" : "235",
    "display" : "Soins intensifs en néonatologie"
  },
  {
    "code" : "241",
    "display" : "Hygiène alimentaire (activité des centres d'hygiène alimentaire notamment)"
  },
  {
    "code" : "309",
    "display" : "Interruption volontaire de grossesse"
  },
  {
    "code" : "384",
    "display" : "Protection maternelle et infantile (centre de PMI ou dispensaire de PMI)"
  },
  {
    "code" : "385",
    "display" : "Consultations prénuptiales, prénatales ou postnatales"
  },
  {
    "code" : "386",
    "display" : "Consultations de protection infantile"
  },
  {
    "code" : "389",
    "display" : "Lutte contre la stérilité"
  },
  {
    "code" : "390",
    "display" : "Consultations de conseil génétique"
  },
  {
    "code" : "391",
    "display" : "Consultations de planification ou d'éducation familiale"
  },
  {
    "code" : "392",
    "display" : "Information, consultation ou conseil familial"
  },
  {
    "code" : "394",
    "display" : "Lactarium"
  },
  {
    "code" : "395",
    "display" : "Guidance parentale"
  },
  {
    "code" : "396",
    "display" : "Guidance infantile"
  },
  {
    "code" : "446",
    "display" : "Médecine scolaire"
  },
  {
    "code" : "447",
    "display" : "Médecine universitaire"
  },
  {
    "code" : "448",
    "display" : "Médecine sportive"
  },
  {
    "code" : "452",
    "display" : "Aide aux insuffisants respiratoires"
  },
  {
    "code" : "552",
    "display" : "Entraînement à l'hémodialyse "
  },
  {
    "code" : "553",
    "display" : "Entraînement à la dialyse péritonéale"
  },
  {
    "code" : "555",
    "display" : "Dialyse péritonéale automatisée à domicile"
  },
  {
    "code" : "556",
    "display" : "Dialyse péritonéale continue ambulatoire à domicile"
  },
  {
    "code" : "596",
    "display" : "Médecine du travail"
  },
  {
    "code" : "631",
    "display" : "Gynécologie seule"
  },
  {
    "code" : "634",
    "display" : "Laboratoire de  radio-isotopes (Médecine nucléaire in vivo)"
  },
  {
    "code" : "635",
    "display" : "Réanimation néonatale"
  },
  {
    "code" : "645",
    "display" : "Oxygénothérapie isolée (insuffisants respiratoires)"
  },
  {
    "code" : "646",
    "display" : "Assistance ventilatoire sans trachéotomie (insuffisants respiratoires)"
  },
  {
    "code" : "647",
    "display" : "Assistance ventilatoire endotrachéale (insuffisants respiratoires)"
  },
  {
    "code" : "648",
    "display" : "Trachéotomie isolée (insuffisants respiratoires)"
  },
  {
    "code" : "665",
    "display" : "Fabrication et distribution indifférenciées de produits pharmaceutiques"
  },
  {
    "code" : "700",
    "display" : "Fabrication, conditionnement et importation de produits cosmétiques et de produits d'hygiène corp."
  },
  {
    "code" : "701",
    "display" : "Fabrication de produits diététiques"
  },
  {
    "code" : "702",
    "display" : "Préparation et vente en gros de produits vétérinaires"
  },
  {
    "code" : "703",
    "display" : "Fabrication (ou importation) de radio-éléments artificiels"
  },
  {
    "code" : "704",
    "display" : "Détention d'animaux en vue de l'expérimentation des médicaments"
  },
  {
    "code" : "705",
    "display" : "Fabrication d'objets contraceptifs"
  },
  {
    "code" : "723",
    "display" : "Hémodialyse à domicile"
  },
  {
    "code" : "726",
    "display" : "Consultations multidisciplines regroupées (médecine, chirurgie et autres spécialités)"
  },
  {
    "code" : "727",
    "display" : "Consultations externes indifférenciées"
  },
  {
    "code" : "743",
    "display" : "Immunohématologie"
  },
  {
    "code" : "745",
    "display" : "Hémostase"
  },
  {
    "code" : "750",
    "display" : "Tomographie"
  },
  {
    "code" : "751",
    "display" : "Radiologie vasculaire"
  },
  {
    "code" : "752",
    "display" : "Echographie sans autre indication (sai)"
  },
  {
    "code" : "753",
    "display" : "Imagerie par résonance magnétique (IRM)"
  },
  {
    "code" : "754",
    "display" : "Autres activités spécialisées d'imagerie médicale"
  },
  {
    "code" : "755",
    "display" : "Explorations fonctionnelles en ORL"
  },
  {
    "code" : "756",
    "display" : "Explorations fonctionnelles en ophtalmologie"
  },
  {
    "code" : "757",
    "display" : "Recherche et expérimentation dans les services médico-techniques"
  },
  {
    "code" : "760",
    "display" : "Salle de réveil"
  },
  {
    "code" : "761",
    "display" : "Anesthésiologie et salle de réveil"
  },
  {
    "code" : "762",
    "display" : "Bloc opératoire et stérilisation indifférenciés"
  },
  {
    "code" : "763",
    "display" : "Pharmacie et stérilisation indifférenciées"
  },
  {
    "code" : "797",
    "display" : "Hémodialyse en centre pour adulte"
  },
  {
    "code" : "798",
    "display" : "Hémodialyse en centre pour enfant"
  },
  {
    "code" : "799",
    "display" : "Assistance ventilatoire avec prothèse extrathoracique(insuffisants respiratoires)"
  },
  {
    "code" : "800",
    "display" : "Assistance ventilatoire par pression positive continue ou autres techniques particulières agréées (insuffisants respiratoires)"
  },
  {
    "code" : "815",
    "display" : "Echocardiologie"
  },
  {
    "code" : "816",
    "display" : "Echographie abdominale"
  },
  {
    "code" : "817",
    "display" : "Echographie en obstétrique"
  },
  {
    "code" : "818",
    "display" : "Echographie vasculaire"
  },
  {
    "code" : "819",
    "display" : "Autres échographies"
  },
  {
    "code" : "820",
    "display" : "Collecte de sang"
  },
  {
    "code" : "821",
    "display" : "Stockage-distribution de sang"
  },
  {
    "code" : "822",
    "display" : "Production de produits sanguins"
  },
  {
    "code" : "823",
    "display" : "Autres activités de transfusion sanguine"
  },
  {
    "code" : "824",
    "display" : "Pharmacie d'établissement"
  },
  {
    "code" : "949",
    "display" : "Recherche chirurgicale ou chirurgie expérimentale"
  },
  {
    "code" : "952",
    "display" : "Recherche médicale"
  },
  {
    "code" : "953",
    "display" : "Recherche pharmacologique"
  },
  {
    "code" : "954",
    "display" : "Recherche pharmaceutique"
  },
  {
    "code" : "955",
    "display" : "Recherche odontologique"
  },
  {
    "code" : "956",
    "display" : "Recherche toxicologique"
  },
  {
    "code" : "996",
    "display" : "Services extérieurs"
  },
  {
    "code" : "997",
    "display" : "Discipline non dénommée ailleurs"
  }]
}