{
  "resourceType" : "ValueSet",
  "id" : "8630031a-2638-4ffe-b32f-7ef75b57a5ea-386",
  "url" : "http://hl7.org/fhir/comparison/ValueSet/8630031a-2638-4ffe-b32f-7ef75b57a5ea-386",
  "name" : "UnionFRCoreValueSetPractitionerRoleExerciceAndFRCoreValueSetPractitionerRoleExercice",
  "title" : "Union of FR Core ValueSet PractitionerRole Exercice And FR Core ValueSet PractitionerRole Exercice",
  "status" : "active",
  "date" : "2025-11-18T17:22:13+00:00",
  "jurisdiction" : [{
    "coding" : [{
      "system" : "urn:iso:std:iso:3166",
      "code" : "FR",
      "display" : "France"
    }]
  }],
  "compose" : {
    "include" : [{
      
    },
    {
      
    },
    {
      
    },
    {
      
    },
    {
      
    },
    {
      
    },
    {
      
    },
    {
      
    },
    {
      
    },
    {
      
    },
    {
      "system" : "https://mos.esante.gouv.fr/NOS/TRE_R24-TypeActiviteLiberale/FHIR/TRE-R24-TypeActiviteLiberale"
    }]
  }
}