{
  "resourceType" : "ValueSet",
  "id" : "e601d2bb-c0ea-4025-b59f-c42c163dc354-404",
  "url" : "http://hl7.org/fhir/comparison/ValueSet/e601d2bb-c0ea-4025-b59f-c42c163dc354-404",
  "name" : "UnionFRCoreValueSetOrganizationTypeAndFRCoreValueSetOrganizationType",
  "title" : "Union of FR Core ValueSet Organization type And FR Core ValueSet Organization type",
  "status" : "active",
  "date" : "2025-12-05T17:13:21+00:00",
  "jurisdiction" : [{
    "coding" : [{
      "system" : "urn:iso:std:iso:3166",
      "code" : "FR",
      "display" : "France"
    }]
  }],
  "compose" : {
    "include" : [{
      "concept" : [{
        "code" : "GHT",
        "display" : "Groupement hospitalier de territoire"
      },
      {
        "code" : "LEGAL-ENTITY",
        "display" : "Entité juridique"
      },
      {
        "code" : "GEOGRAPHICAL-ENTITY",
        "display" : "Entité géographique"
      },
      {
        "code" : "GROUP",
        "display" : "Groupe privé / hospitalier"
      },
      {
        "code" : "HEBERGEMENT",
        "display" : "Hébergement"
      },
      {
        "code" : "SOIN",
        "display" : "Soin"
      },
      {
        "code" : "ADMINISTRATIF",
        "display" : "Administration"
      },
      {
        "code" : "MEDICAL",
        "display" : "Médical"
      },
      {
        "code" : "TECHNIQUE",
        "display" : "Technique"
      },
      {
        "code" : "MEDICOTEC",
        "display" : "medico technique (radio, scanner …)"
      },
      {
        "code" : "UF",
        "display" : "Unité fonctionnelle"
      },
      {
        "code" : "SERVICE",
        "display" : "Service"
      },
      {
        "code" : "UM",
        "display" : "Unité médicale"
      },
      {
        "code" : "UAC",
        "display" : "Unité d'activité"
      },
      {
        "code" : "POLE",
        "display" : "Pole"
      },
      {
        "code" : "CENTRE-RESP",
        "display" : "Centre de responsabilité"
      },
      {
        "code" : "CENTRE-ACTIVITE",
        "display" : "Centre d'activité"
      }]
    }]
  }
}