{
  "resourceType" : "ValueSet",
  "id" : "c32b34d8-3ad8-45d9-a3bc-0f80950f2033-345",
  "url" : "http://hl7.org/fhir/comparison/ValueSet/c32b34d8-3ad8-45d9-a3bc-0f80950f2033-345",
  "name" : "IntersectionFRCoreValueSetBPMeasurementMethodAndFRCoreValueSetBPMeasurementMethod",
  "title" : "Intersection of FR Core ValueSet BP measurement method And FR Core ValueSet BP measurement method",
  "status" : "active",
  "date" : "2025-11-07T16:52:09+00:00",
  "jurisdiction" : [{
    "coding" : [{
      "system" : "urn:iso:std:iso:3166",
      "code" : "FR",
      "display" : "France"
    }]
  }],
  "compose" : {
    "include" : [{
      "concept" : [{
        "code" : "37931006",
        "display" : "Auscultation (procedure)"
      },
      {
        "code" : "113011001",
        "display" : "Palpation (procedure)"
      },
      {
        "code" : "61284002",
        "display" : "Machine, device (physical object)"
      },
      {
        "code" : "10179008",
        "display" : "Invasive (qualifier value)"
      }]
    }]
  }
}