{
  "resourceType" : "ValueSet",
  "id" : "c32b34d8-3ad8-45d9-a3bc-0f80950f2033-194",
  "url" : "http://hl7.org/fhir/comparison/ValueSet/c32b34d8-3ad8-45d9-a3bc-0f80950f2033-194",
  "name" : "UnionSNOMEDCTRouteCodesAndSNOMEDCTRouteCodes",
  "title" : "Union of SNOMED CT Route Codes And SNOMED CT Route Codes",
  "status" : "draft",
  "date" : "2025-11-07T16:52:09+00:00",
  "compose" : {
    "include" : [{
      "filter" : [{
        "property" : "concept",
        "op" : "is-a",
        "value" : "284009009"
      }]
    }]
  }
}