{
  "resourceType" : "ValueSet",
  "id" : "9f93cd5f-7251-475f-aa84-07fb857801d4-395",
  "url" : "http://hl7.org/fhir/comparison/ValueSet/9f93cd5f-7251-475f-aa84-07fb857801d4-395",
  "name" : "UnionPatientRelationshipTypeAndPatientRelationshipType",
  "title" : "Union of Patient relationship type And Patient relationship type",
  "status" : "draft",
  "date" : "2025-12-09T22:52:50+00:00",
  "compose" : {
    "include" : [{
      
    },
    {
      "filter" : [{
        "property" : "concept",
        "op" : "is-a",
        "value" : "_PersonalRelationshipRoleType"
      }]
    }]
  }
}